sanic_nacos/__init__.py
sanic_nacos/sanic_nacos.py
sanic_nacos-1.0.0.dist-info/LICENSE
sanic_nacos-1.0.0.dist-info/METADATA
sanic_nacos-1.0.0.dist-info/WHEEL
sanic_nacos-1.0.0.dist-info/top_level.txt
sanic_nacos-1.0.0.dist-info/RECORD
