Metadata-Version: 2.1
Name: sanic-nacos
Version: 1.0.0
Summary: A Nacos discovery registry for Sanic
Author-email: renqiang <mail.renqiang@gmail.com>
License: MIT License
Project-URL: Homepage, https://github.com/Renz7/sanic_nacos
Project-URL: Issues, https://github.com/Renz7/sanic_nacos/issues
Classifier: Programming Language :: Python :: 3
Classifier: License :: OSI Approved :: MIT License
Classifier: Operating System :: OS Independent
Requires-Python: >=3.8
License-File: LICENSE
Requires-Dist: sanic
Requires-Dist: sanic-ext
Requires-Dist: nacos-sdk-python >=1.0.0
